README.md
setup.py
prtask/__init__.py
prtask.egg-info/PKG-INFO
prtask.egg-info/SOURCES.txt
prtask.egg-info/dependency_links.txt
prtask.egg-info/requires.txt
prtask.egg-info/top_level.txt
prtask/config/__init__.py
prtask/config/main.py
prtask/core/__init__.py
prtask/core/aioRedis.py
prtask/log/__init__.py
prtask/log/log.py