Metadata-Version: 2.1
Name: prtask
Version: 0.1.0
Summary: prtask
Home-page: https://github.com/yourusername/my-package
Author: penr
Author-email: 1944542244@qq.com
License: MIT
Platform: UNKNOWN
Requires-Python: >=3.7
